figanos/__init__.py
figanos/_data.py
figanos/_logo.py
figanos/_testing.py
figanos/data/figanos_logo.png
figanos/data/terms.yml
figanos/data/ipcc_colors/README.md
figanos/data/ipcc_colors/categorical_colors.json
figanos/data/ipcc_colors/variable_groups.json
figanos/data/ipcc_colors/categorical_colors_rgb_0-255/bright_cat.txt
figanos/data/ipcc_colors/categorical_colors_rgb_0-255/chem_cat.txt
figanos/data/ipcc_colors/categorical_colors_rgb_0-255/cmip_cat.txt
figanos/data/ipcc_colors/categorical_colors_rgb_0-255/contrast_cat.txt
figanos/data/ipcc_colors/categorical_colors_rgb_0-255/dark_cat.txt
figanos/data/ipcc_colors/categorical_colors_rgb_0-255/gree-blue_cat.txt
figanos/data/ipcc_colors/categorical_colors_rgb_0-255/rcp_cat.txt
figanos/data/ipcc_colors/categorical_colors_rgb_0-255/red-yellow_cat.txt
figanos/data/ipcc_colors/categorical_colors_rgb_0-255/spectrum_cat.txt
figanos/data/ipcc_colors/categorical_colors_rgb_0-255/ssp_cat_1.txt
figanos/data/ipcc_colors/categorical_colors_rgb_0-255/ssp_cat_2.txt
figanos/data/ipcc_colors/continuous_colormaps_rgb_0-255/chem_div.txt
figanos/data/ipcc_colors/continuous_colormaps_rgb_0-255/chem_seq.txt
figanos/data/ipcc_colors/continuous_colormaps_rgb_0-255/cryo_div.txt
figanos/data/ipcc_colors/continuous_colormaps_rgb_0-255/cryo_seq.txt
figanos/data/ipcc_colors/continuous_colormaps_rgb_0-255/misc_div.txt
figanos/data/ipcc_colors/continuous_colormaps_rgb_0-255/misc_seq_1.txt
figanos/data/ipcc_colors/continuous_colormaps_rgb_0-255/misc_seq_2.txt
figanos/data/ipcc_colors/continuous_colormaps_rgb_0-255/misc_seq_3.txt
figanos/data/ipcc_colors/continuous_colormaps_rgb_0-255/prec_div.txt
figanos/data/ipcc_colors/continuous_colormaps_rgb_0-255/prec_seq.txt
figanos/data/ipcc_colors/continuous_colormaps_rgb_0-255/slev_div.txt
figanos/data/ipcc_colors/continuous_colormaps_rgb_0-255/slev_seq.txt
figanos/data/ipcc_colors/continuous_colormaps_rgb_0-255/temp_div.txt
figanos/data/ipcc_colors/continuous_colormaps_rgb_0-255/temp_seq.txt
figanos-0.6.0.dist-info/licenses/LICENSE
figanos-0.6.0.dist-info/WHEEL
figanos-0.6.0.dist-info/METADATA
figanos-0.6.0.dist-info/RECORD
