Metadata-Version: 2.4
Name: figanos
Version: 0.6.0
Summary: Outils pour produire des graphiques informatifs sur les impacts des changements climatiques.
Keywords: figanos
Author-email: Sarah-Claude Bourdeau-Goulet <bourdeau-goulet.sarah-claude@ouranos.ca>, Juliette Lavoie <lavoie.juliette@ouranos.ca>, Alexis Beaupré-Laperrière <Beaupre-Laperriere.Alexis@ouranos.ca>
Maintainer-email: Sarah-Claude Bourdeau-Goulet <bourdeau-goulet.sarah-claude@ouranos.ca>, Juliette Lavoie <lavoie.juliette@ouranos.ca>, Trevor James Smith <smith.trevorj@ouranos.ca>
Requires-Python: >=3.10.0
License-Expression: Apache-2.0
Classifier: Development Status :: 3 - Alpha
Classifier: Intended Audience :: Developers
Classifier: Natural Language :: English
Classifier: Operating System :: OS Independent
Classifier: Programming Language :: Python :: 3
Classifier: Programming Language :: Python :: 3 :: Only
Classifier: Programming Language :: Python :: 3.10
Classifier: Programming Language :: Python :: 3.11
Classifier: Programming Language :: Python :: 3.12
Classifier: Programming Language :: Python :: 3.13
Classifier: Programming Language :: Python :: 3.14
Classifier: Programming Language :: Python :: Implementation :: CPython
Classifier: Typing :: Typed
License-File: LICENSE
Requires-Dist: cartopy >=0.23.0
Requires-Dist: cairosvg >=2.6.0
Requires-Dist: geopandas >=1.0
Requires-Dist: matplotlib >=3.8.0
Requires-Dist: numpy >=1.25.0
Requires-Dist: pandas >=2.2.0
Requires-Dist: pint >=0.18
Requires-Dist: platformdirs >=4.0
Requires-Dist: pyyaml >=6.0.1
Requires-Dist: seaborn >=0.13.0
Requires-Dist: scikit-image >=0.21.0
Requires-Dist: xarray >=2023.11.0
Requires-Dist: xclim >=0.52.2
Requires-Dist: xsdba >=0.4.0
Requires-Dist: figanos[dev] ; extra == "all"
Requires-Dist: figanos[docs] ; extra == "all"
Requires-Dist: bump-my-version >=1.2.3 ; extra == "dev"
Requires-Dist: coverage >=7.5.0 ; extra == "dev"
Requires-Dist: deptry >=0.23.1 ; extra == "dev"
Requires-Dist: flake8 >=7.3.0 ; extra == "dev"
Requires-Dist: flake8-rst-docstrings >=0.4.0 ; extra == "dev"
Requires-Dist: flit >=3.11.0,<4.0 ; extra == "dev"
Requires-Dist: mypy >=1.18.2 ; extra == "dev"
Requires-Dist: numpydoc >=1.9.0 ; extra == "dev"
Requires-Dist: pip >=25.2 ; extra == "dev"
Requires-Dist: pre-commit >=3.5.0 ; extra == "dev"
Requires-Dist: pytest >=8.3.2 ; extra == "dev"
Requires-Dist: pytest-cov >=5.0.0 ; extra == "dev"
Requires-Dist: ruff >=0.14.3 ; extra == "dev"
Requires-Dist: tox >=4.30.3 ; extra == "dev"
Requires-Dist: vulture >=2.14 ; extra == "dev"
Requires-Dist: watchdog >=4.0.0 ; extra == "dev"
Requires-Dist: dask ; extra == "docs"
Requires-Dist: geoviews ; extra == "docs"
Requires-Dist: h5py ; extra == "docs"
Requires-Dist: holoviews ; extra == "docs"
Requires-Dist: netcdf4 ; extra == "docs"
Requires-Dist: pooch >=1.8.0 ; extra == "docs"
Requires-Dist: zarr >=2.13.0 ; extra == "docs"
Requires-Dist: ipykernel ; extra == "docs"
Requires-Dist: ipython >=8.5.0,!=9.0.0 ; extra == "docs"
Requires-Dist: jupyter_client ; extra == "docs"
Requires-Dist: nbsphinx >=0.9.8 ; extra == "docs"
Requires-Dist: notebook ; extra == "docs"
Requires-Dist: sphinx >=8.2 ; extra == "docs"
Requires-Dist: sphinx-book-theme >=1.0 ; extra == "docs"
Requires-Dist: sphinx-codeautolink >=0.16.2 ; extra == "docs"
Requires-Dist: sphinx-copybutton ; extra == "docs"
Requires-Dist: sphinx-intl ; extra == "docs"
Project-URL: About Ouranos, https://ouranos.ca/en/
Project-URL: Changelog, https://figanos.readthedocs.io/en/stable/changelog.html
Project-URL: Homepage, https://figanos.readthedocs.io/
Project-URL: Issue tracker, https://github.com/Ouranosinc/figanos/issues
Project-URL: Source, https://github.com/Ouranosinc/figanos
Provides-Extra: all
Provides-Extra: dev
Provides-Extra: docs
